faerun_notebook/__init__.py
faerun_notebook/_version.py
faerun_notebook/faerun.py
faerun_notebook/helpers.py
faerun_notebook/smiles_drawer.py
faerun_notebook/labextension/package.json
faerun_notebook/labextension/static/261.75fe5298375c390cf69c.js
faerun_notebook/labextension/static/261.75fe5298375c390cf69c.js.LICENSE.txt
faerun_notebook/labextension/static/486.e9ab49567e714870e78a.js
faerun_notebook/labextension/static/486.e9ab49567e714870e78a.js.LICENSE.txt
faerun_notebook/labextension/static/568.69434fc009826a00ec07.js
faerun_notebook/labextension/static/690.0db0c4e193624b2b0ea6.js
faerun_notebook/labextension/static/767.3c26e792cb811f7a4e39.js
faerun_notebook/labextension/static/923.14ce7d810fd4c513804e.js
faerun_notebook/labextension/static/925.ee61ef9c2541f0f60e1a.js
faerun_notebook/labextension/static/remoteEntry.0f736c3bbe53c7f63673.js
faerun_notebook/labextension/static/style.js
faerun_notebook/labextension/static/third-party-licenses.json
faerun_notebook/nbextension/extension.js
faerun_notebook/nbextension/index.js
faerun_notebook/nbextension/index.js.LICENSE.txt
faerun_notebook-0.1.6b0.data/data/etc/jupyter/nbconfig/notebook.d/faerun-notebook.json
faerun_notebook-0.1.6b0.data/data/share/jupyter/labextensions/faerun-notebook/install.json
faerun_notebook-0.1.6b0.data/data/share/jupyter/labextensions/faerun-notebook/package.json
faerun_notebook-0.1.6b0.data/data/share/jupyter/labextensions/faerun-notebook/static/261.75fe5298375c390cf69c.js
faerun_notebook-0.1.6b0.data/data/share/jupyter/labextensions/faerun-notebook/static/261.75fe5298375c390cf69c.js.LICENSE.txt
faerun_notebook-0.1.6b0.data/data/share/jupyter/labextensions/faerun-notebook/static/486.e9ab49567e714870e78a.js
faerun_notebook-0.1.6b0.data/data/share/jupyter/labextensions/faerun-notebook/static/486.e9ab49567e714870e78a.js.LICENSE.txt
faerun_notebook-0.1.6b0.data/data/share/jupyter/labextensions/faerun-notebook/static/568.69434fc009826a00ec07.js
faerun_notebook-0.1.6b0.dist-info/METADATA
faerun_notebook-0.1.6b0.dist-info/WHEEL
faerun_notebook-0.1.6b0.dist-info/top_level.txt
faerun_notebook-0.1.6b0.dist-info/RECORD
