Metadata-Version: 2.1
Name: faerun-notebook
Version: 0.1.6b0
Summary: A widget for visualising *large* data sets.
Home-page: https://github.com//faerun-notebook
Author: Daniel Probst
Author-email: daenuprobst@gmail.com
Keywords: ipython,jupyter,widgets
Classifier: Development Status :: 4 - Beta
Classifier: Framework :: IPython
Classifier: Intended Audience :: Developers
Classifier: Intended Audience :: Science/Research
Classifier: Topic :: Multimedia :: Graphics
Classifier: Programming Language :: Python :: 3.6
Classifier: Programming Language :: Python :: 3.7
Classifier: Programming Language :: Python :: 3.8
Classifier: Programming Language :: Python :: 3.9
Requires-Dist: ipywidgets (>=7.6.0)
Requires-Dist: numpy
Requires-Dist: matplotlib
